{"activityEntities":["dataSourceCreated",[{"createdDate":"2025-06-02T22:41:53Z","id":"57716D72-3A3E-4DF1-9033-1FC99F700ECD","title":"Data Source Created","event":"dataSourceCreated","subtitle":"Skin Cancer Dataset"}]],"pathType":0,"modifiedDate":"2025-06-02T22:41:53Z","preferredFilename":"Skin Cancer Dataset","createdDate":"2025-06-02T22:41:53Z","dataURL":"file:\/\/\/Users\/sukanyadhiman\/OwnStudy\/Other\/SkinCancerApp\/ML_Models\/Skin%20Cancer%20Dataset\/","dataPathRelativeToProjectURL":"..\/Skin%20Cancer%20Dataset\/","experimentIDs":["C494D2F5-0998-4ECC-8F42-9C2F4AA03B28"],"version":"1.0","id":"220D39DF-9111-4D23-A4A6-B37793E21449","title":"Skin Cancer Dataset","dataResult":{"dataSourceID":"220D39DF-9111-4D23-A4A6-B37793E21449","createdDate":"2025-06-02T22:41:53Z","dataURL":"file:\/\/\/Users\/sukanyadhiman\/OwnStudy\/Other\/SkinCancerApp\/ML_Models\/Skin%20Cancer%20Dataset\/"}}